pwlk/controls.py
pwlk-0.0.1.dist-info/LICENSE
pwlk-0.0.1.dist-info/METADATA
pwlk-0.0.1.dist-info/WHEEL
pwlk-0.0.1.dist-info/top_level.txt
pwlk-0.0.1.dist-info/RECORD
