Metadata-Version: 2.1
Name: pwlk
Version: 0.0.1
Summary: Personnal utility toolbox package
Author: Pawlicki Loïc
Project-URL: Homepage, https://github.com/Lpwlk/pwlk
Classifier: Programming Language :: Python :: 3
Classifier: License :: OSI Approved :: MIT License
Classifier: Operating System :: OS Independent
Requires-Python: >=3.9
License-File: LICENSE
